egp_genomic_library/__init__.py
egp_genomic_library/entry_validator.py
egp_genomic_library/gc_type.py
egp_genomic_library/genomic_library.py
egp_genomic_library/data/codons.json
egp_genomic_library/data/gc_types.json
egp_genomic_library/data/mutations.json
egp_genomic_library/formats/entry_format.json
egp_genomic_library/formats/table_format.json
egp_genomic_library/utils/base_validator.py
egp_genomic_library/utils/reference.py
egp_genomic_library/utils/text_token.py
egp_genomic_library-0.0.1.dev1.dist-info/METADATA
egp_genomic_library-0.0.1.dev1.dist-info/WHEEL
egp_genomic_library-0.0.1.dev1.dist-info/top_level.txt
egp_genomic_library-0.0.1.dev1.dist-info/RECORD
